[{"motion_name":"單仲偕議員對葛珮帆議員的「幫助中產」議案作出的修正案","simplified_name":"動議設各項稅務優惠幫助中產","keywords":"稅制、中產、15年免費教育、侍產假、醫療私營化","note":"增加子女免稅額，調高薪俸稅及個人入息課稅免稅額，增設「居所租金扣稅額」，為購買醫療保險人士提供稅務優惠，制訂僱員侍產假，增加託兒及護老服務，落實15年免費教育","date":"Jan 23, 2013 12:00:00 AM","tags":["中產","中產人士","勞工","家庭照顧者","教育","普通打工仔","有年幼子女","有青少年子女","沒有，但可能打算生育","白領","租住私樓","藍領","醫療"],"parties":{"西九新動力":{"棄權":["梁美芬"]},"民主黨":{"贊成":["單仲偕","黃碧雲","胡志偉","涂謹申","劉慧卿"],"缺席":["何俊仁"]},"人民力量":{"贊成":["黃毓民","陳偉業","陳志全"]},"社民連":{"缺席":["梁國雄"]},"民建聯":{"贊成":["蔣麗芸","何俊賢","陳克勤","鍾樹根","陳鑑林","陳恒鑌","葉國謙","葛珮帆","黃定光","譚耀宗","李慧琼"],"出席":["曾鈺成"],"缺席":["梁志祥"]},"工黨":{"贊成":["張國柱","李卓人","何秀蘭","張超雄"]},"工聯會":{"缺席":["郭偉强","陳婉嫻","王國興","鄧家彪","麥美娟","黃國健"]},"新同盟":{"贊成":["范國威"]},"新民黨":{"反對":["葉劉淑儀","田北辰"]},"民協":{"贊成":["馮檢基"]},"新論壇":{"棄權":["馬逢國"]},"經濟動力":{"棄權":["林健鋒","梁君彥"],"缺席":["劉皇發"]},"公共專業聯盟":{"贊成":["莫乃光","梁繼昌"]},"自由黨":{"贊成":["易志明","田北俊","方剛","張宇人"],"缺席":["鍾國斌"]},"無黨籍":{"贊成":["葉建源","謝偉俊","梁家騮","陳健波"],"反對":["林大輝"],"棄權":["吳亮星","姚思榮","石禮謙","張華峰","謝偉銓","盧偉國","廖長江"],"缺席":["李國麟"]},"勞聯":{"缺席":["潘兆平"]},"公民黨":{"贊成":["梁家傑","湯家驊","陳家洛","毛孟靜","郭榮鏗","郭家麒"]},"街工":{"贊成":["梁耀忠"]}}},{"motion_name":"張國柱議員對陳克勤議員的「關注青年人面對的學業、就業、住屋置業和創業問題」議案作出的修正案","simplified_name":"「關注青年人面對的學業、就業、住屋置業和創業問題」議案的修正案","keywords":"青年、最低工資、實習、公屋輪候","note":"修訂《最低工資條例》至涵蓋工作少於59天的大學實習生，提高申請公屋的入息和資產上限、增加單身人士配額，並自動登記年滿18歲的香港永久性居民為選民","date":"Nov 28, 2012 12:00:00 AM","tags":["勞工","學生","房屋","政制","有青少年子女","沒有","租住私樓"],"parties":{"西九新動力":{"反對":["梁美芬"]},"民主黨":{"贊成":["劉慧卿","胡志偉","單仲偕","黃碧雲"],"缺席":["涂謹申","何俊仁"]},"人民力量":{"贊成":["陳偉業","黃毓民","陳志全"]},"社民連":{"贊成":["梁國雄"]},"民建聯":{"出席":["曾鈺成"],"反對":["陳克勤","何俊賢","葛珮帆","葉國謙","鍾樹根","陳恒鑌","陳鑑林","李慧琼","蔣麗芸"],"缺席":["黃定光","譚耀宗","梁志祥"]},"工黨":{"贊成":["李卓人","張超雄","張國柱","何秀蘭"]},"工聯會":{"棄權":["鄧家彪","郭偉强","黃國健","王國興","麥美娟","陳婉嫻"]},"新同盟":{"贊成":["范國威"]},"新民黨":{"反對":["葉劉淑儀","田北辰"]},"民協":{"贊成":["馮檢基"]},"新論壇":{"反對":["馬逢國"]},"經濟動力":{"反對":["梁君彥","林健鋒"],"缺席":["劉皇發"]},"公共專業聯盟":{"反對":["梁繼昌","莫乃光"]},"自由黨":{"反對":["方剛","鍾國斌"],"缺席":["田北俊","易志明","張宇人"]},"無黨籍":{"贊成":["葉建源","梁家騮"],"反對":["謝偉俊","廖長江","盧偉國","姚思榮"],"棄權":["謝偉銓","李國麟","陳健波","林大輝"],"缺席":["吳亮星","張華峰","石禮謙"]},"勞聯":{"贊成":["潘兆平"]},"公民黨":{"贊成":["梁家傑","陳家洛","郭榮鏗","郭家麒","湯家驊","毛孟靜"]},"街工":{"贊成":["梁耀忠"]}}},{"motion_name":"張國柱議員對陳婉嫻議員就「紓解貧窮」所提，經馮檢基議員修正的議案，作出的修正案","simplified_name":"動議調高交津計劃入息限額，並推行租務管制","keywords":"交通津貼、租務管制","note":"調高「鼓勵就業交通津貼計劃」入息限額，並推行租務管制，防止業主大幅加租和任意終止租約，保障基層租客權益","date":"Nov 14, 2012 12:00:00 AM","tags":["勞工","家庭照顧者","房屋","普通打工仔","業主","租住私樓"],"parties":{"西九新動力":{"反對":["梁美芬"]},"民主黨":{"贊成":["劉慧卿","涂謹申","胡志偉","單仲偕","何俊仁","黃碧雲"]},"人民力量":{"贊成":["黃毓民","陳志全","陳偉業"]},"社民連":{"贊成":["梁國雄"]},"民建聯":{"出席":["曾鈺成"],"棄權":["梁志祥","陳鑑林","何俊賢","葉國謙","鍾樹根","黃定光","葛珮帆","蔣麗芸","李慧琼","陳克勤","譚耀宗"],"缺席":["陳恒鑌"]},"工黨":{"贊成":["張超雄","何秀蘭","李卓人","張國柱"]},"工聯會":{"贊成":["麥美娟","王國興","郭偉强","黃國健","陳婉嫻","鄧家彪"]},"新同盟":{"贊成":["范國威"]},"新民黨":{"反對":["葉劉淑儀","田北辰"]},"民協":{"贊成":["馮檢基"]},"新論壇":{"棄權":["馬逢國"]},"經濟動力":{"反對":["林健鋒","劉皇發","梁君彥"]},"公共專業聯盟":{"贊成":["梁繼昌","莫乃光"]},"自由黨":{"反對":["田北俊","方剛","易志明","鍾國斌"],"缺席":["張宇人"]},"無黨籍":{"贊成":["李國麟","葉建源"],"反對":["謝偉銓","謝偉俊","張華峰","姚思榮","盧偉國","陳健波","石禮謙","廖長江","林大輝"],"棄權":["梁家騮","吳亮星"]},"勞聯":{"贊成":["潘兆平"]},"公民黨":{"贊成":["郭榮鏗","毛孟靜","陳家洛","湯家驊","郭家麒","梁家傑"]},"街工":{"贊成":["梁耀忠"]}}},{"motion_name":"李卓人議員對王國興議員的「完善房屋政策，解決市民住屋需要」議案作出的修正案","simplified_name":"動議重新推行租務管制","keywords":"租務管制","note":"重新推行租務管制，防止業主大幅加租和任意終止租約，保障私人房屋租客權益","date":"Nov 7, 2012 12:00:00 AM","tags":["房屋","普通打工仔","業主","租住私樓"],"parties":{"西九新動力":{"反對":["梁美芬"]},"民主黨":{"贊成":["何俊仁","涂謹申","劉慧卿","單仲偕","黃碧雲","胡志偉"]},"人民力量":{"贊成":["黃毓民","陳志全"],"缺席":["陳偉業"]},"社民連":{"贊成":["梁國雄"]},"民建聯":{"出席":["曾鈺成"],"棄權":["陳恒鑌","葛珮帆","蔣麗芸","黃定光","陳鑑林","陳克勤","葉國謙","何俊賢","鍾樹根","譚耀宗","李慧琼","梁志祥"]},"工黨":{"贊成":["何秀蘭","李卓人","張國柱","張超雄"]},"工聯會":{"贊成":["王國興","麥美娟","郭偉强","鄧家彪","黃國健"],"缺席":["陳婉嫻"]},"新同盟":{"贊成":["范國威"]},"新民黨":{"反對":["田北辰"],"缺席":["葉劉淑儀"]},"民協":{"贊成":["馮檢基"]},"新論壇":{"反對":["馬逢國"]},"經濟動力":{"反對":["林健鋒","梁君彥"],"缺席":["劉皇發"]},"公共專業聯盟":{"贊成":["莫乃光"],"缺席":["梁繼昌"]},"自由黨":{"反對":["易志明","張宇人","田北俊","鍾國斌","方剛"]},"無黨籍":{"贊成":["葉建源","李國麟"],"反對":["姚思榮","張華峰","吳亮星","石禮謙","盧偉國","陳健波","謝偉銓"],"棄權":["林大輝","謝偉俊","廖長江"],"缺席":["梁家騮"]},"勞聯":{"贊成":["潘兆平"]},"公民黨":{"贊成":["湯家驊","梁家傑","郭榮鏗","陳家洛","郭家麒"],"缺席":["毛孟靜"]},"街工":{"贊成":["梁耀忠"]}}},{"motion_name":"范國威議員根據《立法會（權力及特權）條例》動議的議案","simplified_name":"動議成立專責委員會調查鉛水事件","keywords":"公屋、鉛水","note":"成立專責委員會調查鉛水事件","date":"Oct 16, 2015 12:00:00 AM","tags":["房屋","有年幼子女","有青少年子女","沒有，但可能打算生育","租住公屋","租住私樓"],"parties":{"西九新動力":{"缺席":["梁美芬"]},"民主黨":{"贊成":["何俊仁","黃碧雲","劉慧卿","涂謹申","單仲偕","胡志偉"]},"人民力量":{"贊成":["陳偉業","陳志全"]},"社民連":{"贊成":["梁國雄"]},"普羅政治學苑":{"贊成":["黃毓民"]},"民建聯":{"出席":["曾鈺成"],"反對":["葉國謙","葛珮帆","梁志祥","陳鑑林","李慧琼","何俊賢","陳克勤","鍾樹根","黃定光","陳恒鑌","譚耀宗"],"缺席":["蔣麗芸"]},"工黨":{"贊成":["張國柱","李卓人","何秀蘭"],"缺席":["張超雄"]},"工聯會":{"反對":["鄧家彪","黃國健","郭偉强","陳婉嫻","麥美娟","王國興"]},"新同盟":{"贊成":["范國威"]},"新民黨":{"反對":["田北辰","葉劉淑儀"]},"民協":{"贊成":["馮檢基"]},"新論壇":{"反對":["馬逢國"]},"經濟動力":{"反對":["林健鋒","梁君彥"],"缺席":["劉皇發"]},"公共專業聯盟":{"贊成":["梁繼昌","莫乃光"]},"自由黨":{"反對":["張宇人","方剛","鍾國斌","易志明"],"缺席":["田北俊"]},"無黨籍":{"贊成":["李國麟","葉建源"],"反對":["謝偉俊","謝偉銓","盧偉國","吳亮星","姚思榮","張華峰","陳健波","廖長江","石禮謙"],"缺席":["林大輝","梁家騮"]},"勞聯":{"反對":["潘兆平"]},"公民黨":{"贊成":["毛孟靜","郭家麒","陳家洛","郭榮鏗","梁家傑"]},"街工":{"贊成":["梁耀忠"]}}},{"motion_name":"郭家麒議員對謝偉銓議員的「制訂住屋開支比例目標及人均居住面積標準」議案作出的修正案","simplified_name":"要求改善劏房戶居住環境","keywords":"劏房、臨屋","note":"要求改善劏房戶居住環境，並盡快提供足夠臨時房屋","date":"Oct 10, 2013 12:00:00 AM","tags":["房屋","普通打工仔","業主","租住私樓"],"parties":{"西九新動力":{"棄權":["梁美芬"]},"民主黨":{"棄權":["單仲偕","黃碧雲","劉慧卿","胡志偉"],"缺席":["涂謹申","何俊仁"]},"人民力量":{"贊成":["陳偉業","陳志全"]},"社民連":{"贊成":["梁國雄"]},"普羅政治學苑":{"缺席":["黃毓民"]},"民建聯":{"出席":["曾鈺成"],"棄權":["陳鑑林","鍾樹根","蔣麗芸","陳恒鑌","葛珮帆","黃定光","葉國謙","梁志祥","陳克勤","何俊賢","譚耀宗"],"缺席":["李慧琼"]},"工黨":{"贊成":["何秀蘭","張超雄","張國柱"],"缺席":["李卓人"]},"工聯會":{"棄權":["王國興","郭偉强","麥美娟","黃國健","鄧家彪"],"缺席":["陳婉嫻"]},"新同盟":{"缺席":["范國威"]},"新民黨":{"棄權":["田北辰"],"缺席":["葉劉淑儀"]},"民協":{"贊成":["馮檢基"]},"新論壇":{"棄權":["馬逢國"]},"經濟動力":{"棄權":["梁君彥"],"缺席":["林健鋒","劉皇發"]},"公共專業聯盟":{"贊成":["莫乃光"],"棄權":["梁繼昌"]},"自由黨":{"反對":["田北俊","易志明","方剛","鍾國斌","張宇人"]},"無黨籍":{"反對":["李國麟","姚思榮"],"棄權":["廖長江","葉建源","盧偉國","張華峰","謝偉銓","陳健波"],"缺席":["吳亮星","林大輝","謝偉俊","梁家騮","石禮謙"]},"勞聯":{"棄權":["潘兆平"]},"公民黨":{"贊成":["郭家麒","梁家傑","陳家洛","郭榮鏗"],"缺席":["毛孟靜","湯家驊"]},"街工":{"缺席":["梁耀忠"]}}}]